aws_django_deploy-1.0.2.dist-info/DESCRIPTION.rst
aws_django_deploy-1.0.2.dist-info/METADATA
aws_django_deploy-1.0.2.dist-info/RECORD
aws_django_deploy-1.0.2.dist-info/WHEEL
aws_django_deploy-1.0.2.dist-info/entry_points.txt
aws_django_deploy-1.0.2.dist-info/metadata.json
aws_django_deploy-1.0.2.dist-info/top_level.txt
awsdjangodeploy/__init__.py
awsdjangodeploy/cc.py
awsdjangodeploy/cli.py
