Metadata-Version: 2.0
Name: aws-django-deploy
Version: 1.0.2
Summary: A Python package to deploy django applications on AWS cloud ec2 instance
Home-page: https://github.com/avinashkatariya/awsdjangodeploy
Author: Avinash Katariya
Author-email: avinashkatariya810@gmail.com
License: MIT
Platform: UNKNOWN
Classifier: License :: OSI Approved :: MIT License
Classifier: Programming Language :: Python :: 3
Classifier: Programming Language :: Python :: 3.7
